Workbook
Name aporte: APP!$D$14
Name patrimonio: APP!$D$17
Name qtd_anos: APP!$D$15
Name rendimento_carteira: APP!$D$10
Name salario: APP!$D$9
Name sugestao_investimento: APP!$D$11
Name taxa_mensal: APP!$D$16

Sheet APP
B8: CONFIGURAÇÕES
B9: Salário | D9: 3500
B10: Rendimento de Carteira | D10: 0.006
B11: Sugestão de investimento (30%) | D11: =salario*30% -> 1050
B13: INVESTIMENTO MENSAL
B14: Quanto devo investir por mês? | D14: 700
B15: Por quantos anos investir? | D15: 10
B16: Taxa de rendimento mensal? | D16: 0.01079
B17: Quanto de patrimônio acumulado? | D17: =FV(taxa_mensal,qtd_anos*12,aporte*(-1)) -> 170298.95
B18: Quantos dividentos mensais? | D18: =patrimonio*rendimento_carteira -> 1021.7937
B20: Cenários | D20: Dividendos
A21: 2 | B21: Quanto em 02 anos? | C21: =FV(taxa_mensal,A21*12,aporte*(-1)) -> 19059.339 | D21: =C21*rendimento_carteira -> 114.35603
A22: 5 | B22: Quanto em 05 anos? | C22: =FV(taxa_mensal,A22*12,aporte*(-1)) -> 58643.84 | D22: =C22*rendimento_carteira -> 351.86304
A23: 10 | B23: Quanto em 10 anos? | C23: =FV(taxa_mensal,A23*12,aporte*(-1)) -> 170298.95 | D23: =C23*rendimento_carteira -> 1021.7937
A24: 20 | B24: Quanto em 20 anos? | C24: =FV(taxa_mensal,A24*12,aporte*(-1)) -> 787638.88 | D24: =C24*rendimento_carteira -> 4725.8333
A25: 30 | B25: Quanto em 30 anos? | C25: =FV(taxa_mensal,A25*12,aporte*(-1)) -> 3025518.8 | D25: =C25*rendimento_carteira -> 18153.113
B29: PERFIL | C29: Moderado
B30: VALOR A SER INVESTIDO POR MÊS | C30: =aporte -> 700
B32: TIPO DE FII | C32: Percentual sugerido | D32: Valores
B33: PAPEL | C33: =VLOOKUP($C$29&"-"&B33,Chave!$A$2:$D$20,4,FALSE) -> 0.32 | D33: =C33*$C$30 -> 224
B34: TIJOLO | C34: =VLOOKUP($C$29&"-"&B34,Chave!$A$2:$D$20,4,FALSE) -> 0.4 | D34: =C34*$C$30 -> 280
B35: HÍBRIDOS | C35: =VLOOKUP($C$29&"-"&B35,Chave!$A$2:$D$20,4,FALSE) -> 0.08 | D35: =C35*$C$30 -> 56
B36: FOFs | C36: =VLOOKUP($C$29&"-"&B36,Chave!$A$2:$D$20,4,FALSE) -> 0.1 | D36: =C36*$C$30 -> 70
B37: DESENVOLVIMENTO | C37: =VLOOKUP($C$29&"-"&B37,Chave!$A$2:$D$20,4,FALSE) -> 0.1 | D37: =C37*$C$30 -> 70
B38: HOTELARIAS | C38: =VLOOKUP($C$29&"-"&B38,Chave!$A$2:$D$20,4,FALSE) -> 0 | D38: =C38*$C$30 -> 0
D39: =SUM(D33:D38) -> 700

Sheet Chave
A2: CHAVE | B2: PERFIL | C2: TIPO DE FII | D2: %
A3: =$B$3&"-"&C3 -> Conservador-PAPEL | B3: Conservador | C3: PAPEL | D3: 0.3
A4: =$B$3&"-"&C4 -> Conservador-TIJOLO | B4: Conservador | C4: TIJOLO | D4: 0.5
A5: =$B$3&"-"&C5 -> Conservador-HÍBRIDOS | B5: Conservador | C5: HÍBRIDOS | D5: 0.1
A6: =$B$3&"-"&C6 -> Conservador-FOFs | B6: Conservador | C6: FOFs | D6: 0.1
A7: =$B$3&"-"&C7 -> Conservador-DESENVOLVIMENTO | B7: Conservador | C7: DESENVOLVIMENTO | D7: 0
A8: =$B$3&"-"&C8 -> Conservador-HOTELARIAS | B8: Conservador | C8: HOTELARIAS | D8: 0
A9: =$B$9&"-"&C9 -> Moderado-PAPEL | B9: Moderado | C9: PAPEL | D9: 0.32
A10: =$B$9&"-"&C10 -> Moderado-TIJOLO | B10: Moderado | C10: TIJOLO | D10: 0.4
A11: =$B$9&"-"&C11 -> Moderado-HÍBRIDOS | B11: Moderado | C11: HÍBRIDOS | D11: 0.08
A12: =$B$9&"-"&C12 -> Moderado-FOFs | B12: Moderado | C12: FOFs | D12: 0.1
A13: =$B$9&"-"&C13 -> Moderado-DESENVOLVIMENTO | B13: Moderado | C13: DESENVOLVIMENTO | D13: 0.1
A14: =$B$9&"-"&C14 -> Moderado-HOTELARIAS | B14: Moderado | C14: HOTELARIAS | D14: 0
A15: =$B$15&"-"&C15 -> Agressivo-PAPEL | B15: Agressivo | C15: PAPEL | D15: 0.5
A16: =$B$15&"-"&C16 -> Agressivo-TIJOLO | B16: Agressivo | C16: TIJOLO | D16: 0.1
A17: =$B$15&"-"&C17 -> Agressivo-HÍBRIDOS | B17: Agressivo | C17: HÍBRIDOS | D17: 0.05
A18: =$B$15&"-"&C18 -> Agressivo-FOFs | B18: Agressivo | C18: FOFs | D18: 0.05
A19: =$B$15&"-"&C19 -> Agressivo-DESENVOLVIMENTO | B19: Agressivo | C19: DESENVOLVIMENTO | D19: 0.2
A20: =$B$15&"-"&C20 -> Agressivo-HOTELARIAS | B20: Agressivo | C20: HOTELARIAS | D20: 0.1
